manage_server_power/__init__.py
manage_server_power-0.0.6.dist-info/DESCRIPTION.rst
manage_server_power-0.0.6.dist-info/METADATA
manage_server_power-0.0.6.dist-info/RECORD
manage_server_power-0.0.6.dist-info/WHEEL
manage_server_power-0.0.6.dist-info/metadata.json
manage_server_power-0.0.6.dist-info/top_level.txt
