Metadata-Version: 2.0
Name: manage-server-power
Version: 0.0.6
Summary: Small library for shutting down and starting up local server
Home-page: https://github.com/ojarva/python-manage-server-power
Author: Olli Jarva
Author-email: olli@jarva.fi
License: BSD
Keywords: wol wake-on-lan
Platform: UNKNOWN
Classifier: Development Status :: 4 - Beta
Classifier: Intended Audience :: Developers
Classifier: Intended Audience :: System Administrators
Classifier: License :: OSI Approved :: BSD License
Classifier: Programming Language :: Python :: 2.6
Classifier: Programming Language :: Python :: 2.7
Classifier: Programming Language :: Python :: 3
Classifier: Programming Language :: Python :: 3.2
Classifier: Programming Language :: Python :: 3.3
Classifier: Programming Language :: Python :: 3.4
Classifier: Programming Language :: Python :: Implementation :: PyPy
Requires-Dist: paramiko
Requires-Dist: wakeonlan
Provides-Extra: dev
Requires-Dist: twine; extra == 'dev'
Requires-Dist: wheel; extra == 'dev'
